{
  "updated_at": "2025-10-29T06:47:41.110Z",
  "meta": {
    "included_ids": [
      "bitcoin",
      "ethereum",
      "tether",
      "binancecoin",
      "solana",
      "ripple",
      "usd-coin",
      "staked-ether",
      "cardano",
      "dogecoin",
      "avalanche-2",
      "tron",
      "shiba-inu",
      "wrapped-bitcoin",
      "polkadot",
      "chainlink",
      "bitcoin-cash",
      "uniswap",
      "litecoin",
      "internet-computer",
      "dai",
      "near",
      "ethereum-classic",
      "filecoin",
      "aptos",
      "leo-token",
      "stellar",
      "okb",
      "vechain",
      "render-token",
      "monero",
      "arbitrum",
      "fantom",
      "the-graph",
      "immutable-x",
      "maker",
      "kaspa",
      "gala",
      "optimism",
      "frax",
      "sei-network",
      "algorand",
      "flow",
      "thorchain",
      "conflux-token",
      "mina-protocol",
      "worldcoin-wld",
      "polygon-ecosystem-token",
      "bonk",
      "book-of-meme",
      "official-trump",
      "streamflow",
      "pudgy-penguins",
      "just-a-chill-guy",
      "goatseus-maximus"
    ],
    "wallet_resolved": [
      {
        "raw": "worldcoin",
        "resolved": "worldcoin-wld",
        "via": "override"
      },
      {
        "raw": "pol",
        "resolved": "polygon-ecosystem-token",
        "via": "override"
      },
      {
        "raw": "bonk",
        "resolved": "bonk",
        "via": "id"
      },
      {
        "raw": "bome",
        "resolved": "book-of-meme",
        "via": "override"
      },
      {
        "raw": "official-trump",
        "resolved": "official-trump",
        "via": "id"
      },
      {
        "raw": "streamflow",
        "resolved": "streamflow",
        "via": "id"
      },
      {
        "raw": "pengu",
        "resolved": "pudgy-penguins",
        "via": "override"
      },
      {
        "raw": "just-a-chill-guy",
        "resolved": "just-a-chill-guy",
        "via": "id"
      },
      {
        "raw": "goatseus-maximus",
        "resolved": "goatseus-maximus",
        "via": "id"
      },
      {
        "raw": "optimism",
        "resolved": "optimism",
        "via": "id"
      },
      {
        "raw": "solana",
        "resolved": "solana",
        "via": "id"
      },
      {
        "raw": "ripple",
        "resolved": "ripple",
        "via": "id"
      }
    ],
    "missing": [],
    "ambiguous": []
  },
  "assets": {
    "BTC": {
      "usd": 113114,
      "change_24h": -0.8005262936724733,
      "change_7d": 4.584934294778357,
      "market_cap": 2255075425728,
      "id": "bitcoin",
      "name": "Bitcoin",
      "source": "coingecko"
    },
    "ETH": {
      "usd": 4022.15,
      "change_24h": -1.9355418341504147,
      "change_7d": 4.141440641613125,
      "market_cap": 485249241808,
      "id": "ethereum",
      "name": "Ethereum",
      "source": "coingecko"
    },
    "USDT": {
      "usd": 1,
      "change_24h": 0.019338865679521547,
      "change_7d": -0.03410783820430259,
      "market_cap": 183277468887,
      "id": "tether",
      "name": "Tether",
      "source": "coingecko"
    },
    "XRP": {
      "usd": 2.62,
      "change_24h": -0.5531288586401111,
      "change_7d": 7.741022230896473,
      "market_cap": 157507233387,
      "id": "ripple",
      "name": "XRP",
      "source": "coingecko"
    },
    "BNB": {
      "usd": 1119.11,
      "change_24h": -0.9302191076400037,
      "change_7d": 4.162532223948914,
      "market_cap": 154060471520,
      "id": "binancecoin",
      "name": "BNB",
      "source": "coingecko"
    },
    "SOL": {
      "usd": 195.15,
      "change_24h": -2.377540695130609,
      "change_7d": 5.023776914974263,
      "market_cap": 107274615806,
      "id": "solana",
      "name": "Solana",
      "source": "coingecko"
    },
    "USDC": {
      "usd": 0.999896,
      "change_24h": -0.0005200958084911986,
      "change_7d": 0.009115273791623246,
      "market_cap": 76202242214,
      "id": "usd-coin",
      "name": "USDC",
      "source": "coingecko"
    },
    "STETH": {
      "usd": 4021.23,
      "change_24h": -1.890787701700909,
      "change_7d": 4.143213607041103,
      "market_cap": 34530768582,
      "id": "staked-ether",
      "name": "Lido Staked Ether",
      "source": "coingecko"
    },
    "DOGE": {
      "usd": 0.193788,
      "change_24h": -3.3114775196275232,
      "change_7d": -0.5522155048513675,
      "market_cap": 29361033774,
      "id": "dogecoin",
      "name": "Dogecoin",
      "source": "coingecko"
    },
    "TRX": {
      "usd": 0.297325,
      "change_24h": 0.14265736357167472,
      "change_7d": -8.063689144777793,
      "market_cap": 28146845601,
      "id": "tron",
      "name": "TRON",
      "source": "coingecko"
    },
    "ADA": {
      "usd": 0.643897,
      "change_24h": -2.6151227623462727,
      "change_7d": 0.0813376876678743,
      "market_cap": 23546637383,
      "id": "cardano",
      "name": "Cardano",
      "source": "coingecko"
    },
    "WBTC": {
      "usd": 112900,
      "change_24h": -0.800539049593959,
      "change_7d": 4.0004532254240965,
      "market_cap": 14312715883,
      "id": "wrapped-bitcoin",
      "name": "Wrapped Bitcoin",
      "source": "coingecko"
    },
    "LINK": {
      "usd": 17.84,
      "change_24h": -2.096892536708698,
      "change_7d": 0.15022776919382413,
      "market_cap": 12428145712,
      "id": "chainlink",
      "name": "Chainlink",
      "source": "coingecko"
    },
    "BCH": {
      "usd": 561.68,
      "change_24h": 0.31016406207679975,
      "change_7d": 16.250367498160234,
      "market_cap": 11203275403,
      "id": "bitcoin-cash",
      "name": "Bitcoin Cash",
      "source": "coingecko"
    },
    "XLM": {
      "usd": 0.318156,
      "change_24h": -3.6003805404946925,
      "change_7d": 1.1544767144104366,
      "market_cap": 10188660984,
      "id": "stellar",
      "name": "Stellar",
      "source": "coingecko"
    },
    "LEO": {
      "usd": 9.63,
      "change_24h": 2.6872958068770405,
      "change_7d": 7.41980551686527,
      "market_cap": 8885008000,
      "id": "leo-token",
      "name": "LEO Token",
      "source": "coingecko"
    },
    "AVAX": {
      "usd": 19.51,
      "change_24h": -3.7340172853687044,
      "change_7d": 0.28820822552689634,
      "market_cap": 8324529930,
      "id": "avalanche-2",
      "name": "Avalanche",
      "source": "coingecko"
    },
    "LTC": {
      "usd": 97.12,
      "change_24h": -5.178213528635832,
      "change_7d": 4.216816954440423,
      "market_cap": 7424966550,
      "id": "litecoin",
      "name": "Litecoin",
      "source": "coingecko"
    },
    "XMR": {
      "usd": 344.17,
      "change_24h": 0.7255323677466609,
      "change_7d": 11.30403784035593,
      "market_cap": 6348629031,
      "id": "monero",
      "name": "Monero",
      "source": "coingecko"
    },
    "SHIB": {
      "usd": 0.00001013,
      "change_24h": -2.203313927976124,
      "change_7d": 0.38500601837556353,
      "market_cap": 5964802877,
      "id": "shiba-inu",
      "name": "Shiba Inu",
      "source": "coingecko"
    },
    "DOT": {
      "usd": 3.07,
      "change_24h": -2.149381132805254,
      "change_7d": 2.4673552277926243,
      "market_cap": 4663412604,
      "id": "polkadot",
      "name": "Polkadot",
      "source": "coingecko"
    },
    "DAI": {
      "usd": 1,
      "change_24h": 0.030997079857004513,
      "change_7d": -0.07020973286147666,
      "market_cap": 4656790427,
      "id": "dai",
      "name": "Dai",
      "source": "coingecko"
    },
    "UNI": {
      "usd": 6.34,
      "change_24h": -2.4901085151991813,
      "change_7d": 1.2151840129818834,
      "market_cap": 3810528815,
      "id": "uniswap",
      "name": "Uniswap",
      "source": "coingecko"
    },
    "OKB": {
      "usd": 163.59,
      "change_24h": -1.1203594074346739,
      "change_7d": 1.424854838136646,
      "market_cap": 3435464905,
      "id": "okb",
      "name": "OKB",
      "source": "coingecko"
    },
    "NEAR": {
      "usd": 2.24,
      "change_24h": -3.9174919784585183,
      "change_7d": -0.12156143417231646,
      "market_cap": 2864354627,
      "id": "near",
      "name": "NEAR Protocol",
      "source": "coingecko"
    },
    "ETC": {
      "usd": 15.97,
      "change_24h": -2.7710480913780775,
      "change_7d": 2.3604761073371923,
      "market_cap": 2461632972,
      "id": "ethereum-classic",
      "name": "Ethereum Classic",
      "source": "coingecko"
    },
    "APT": {
      "usd": 3.34,
      "change_24h": -3.827051737797153,
      "change_7d": 2.87467809192953,
      "market_cap": 2402114396,
      "id": "aptos",
      "name": "Aptos",
      "source": "coingecko"
    },
    "POL": {
      "usd": 0.194735,
      "change_24h": -2.7490608091501634,
      "change_7d": -0.5281539562514412,
      "market_cap": 2049284479,
      "id": "polygon-ecosystem-token",
      "name": "POL (ex-MATIC)",
      "source": "coingecko"
    },
    "WLD": {
      "usd": 0.86808,
      "change_24h": -3.309270566243868,
      "change_7d": -2.9304535714828295,
      "market_cap": 1958721708,
      "id": "worldcoin-wld",
      "name": "Worldcoin",
      "source": "coingecko"
    },
    "ARB": {
      "usd": 0.317066,
      "change_24h": -3.6231307360322234,
      "change_7d": 3.025874787482757,
      "market_cap": 1746551098,
      "id": "arbitrum",
      "name": "Arbitrum",
      "source": "coingecko"
    },
    "ICP": {
      "usd": 3.06,
      "change_24h": -3.8515051120837915,
      "change_7d": 1.038814433937637,
      "market_cap": 1652577791,
      "id": "internet-computer",
      "name": "Internet Computer",
      "source": "coingecko"
    },
    "ALGO": {
      "usd": 0.182946,
      "change_24h": -6.705195400527407,
      "change_7d": 0.5553941252317988,
      "market_cap": 1607800863,
      "id": "algorand",
      "name": "Algorand",
      "source": "coingecko"
    },
    "KAS": {
      "usd": 0.057524,
      "change_24h": 0.8664264946073301,
      "change_7d": 10.238750364150185,
      "market_cap": 1540184455,
      "id": "kaspa",
      "name": "Kaspa",
      "source": "coingecko"
    },
    "TRUMP": {
      "usd": 7.71,
      "change_24h": 12.631502248712978,
      "change_7d": 31.90556822463385,
      "market_cap": 1531057209,
      "id": "official-trump",
      "name": "Official Trump",
      "source": "coingecko"
    },
    "VET": {
      "usd": 0.01674565,
      "change_24h": -2.8590664363513945,
      "change_7d": -2.0219198803829417,
      "market_cap": 1439756296,
      "id": "vechain",
      "name": "VeChain",
      "source": "coingecko"
    },
    "PENGU": {
      "usd": 0.02076206,
      "change_24h": -1.982760604645626,
      "change_7d": -2.780880888656683,
      "market_cap": 1303438648,
      "id": "pudgy-penguins",
      "name": "Pudgy Penguins",
      "source": "coingecko"
    },
    "RENDER": {
      "usd": 2.42,
      "change_24h": -3.3834555478311117,
      "change_7d": -2.0080302518283264,
      "market_cap": 1252708248,
      "id": "render-token",
      "name": "Render",
      "source": "coingecko"
    },
    "SEI": {
      "usd": 0.195411,
      "change_24h": -2.7225153414425627,
      "change_7d": 2.485492107525409,
      "market_cap": 1221085302,
      "id": "sei-network",
      "name": "Sei",
      "source": "coingecko"
    },
    "BONK": {
      "usd": 0.00001429,
      "change_24h": -3.726318520088847,
      "change_7d": -0.0851358566126225,
      "market_cap": 1106134221,
      "id": "bonk",
      "name": "Bonk",
      "source": "coingecko"
    },
    "FIL": {
      "usd": 1.57,
      "change_24h": -4.1962984400202314,
      "change_7d": 1.2807013977497361,
      "market_cap": 1097358702,
      "id": "filecoin",
      "name": "Filecoin",
      "source": "coingecko"
    },
    "IMX": {
      "usd": 0.519194,
      "change_24h": -0.8176273518020188,
      "change_7d": 1.767235814097615,
      "market_cap": 1019945468,
      "id": "immutable-x",
      "name": "Immutable",
      "source": "coingecko"
    },
    "OP": {
      "usd": 0.435596,
      "change_24h": -4.531031210432192,
      "change_7d": -0.2126254123696154,
      "market_cap": 826050118,
      "id": "optimism",
      "name": "Optimism",
      "source": "coingecko"
    },
    "GRT": {
      "usd": 0.063158,
      "change_24h": -2.5462544491972756,
      "change_7d": 0.32655460364702305,
      "market_cap": 666968383,
      "id": "the-graph",
      "name": "The Graph",
      "source": "coingecko"
    },
    "CFX": {
      "usd": 0.109914,
      "change_24h": -4.823535598493294,
      "change_7d": 0.10058149700909755,
      "market_cap": 565615894,
      "id": "conflux-token",
      "name": "Conflux",
      "source": "coingecko"
    },
    "GALA": {
      "usd": 0.01079738,
      "change_24h": -2.9755473116882096,
      "change_7d": -0.2873382403471973,
      "market_cap": 500678262,
      "id": "gala",
      "name": "GALA",
      "source": "coingecko"
    },
    "FLOW": {
      "usd": 0.268928,
      "change_24h": -2.3348327737877024,
      "change_7d": -0.8048826322949088,
      "market_cap": 435183088,
      "id": "flow",
      "name": "Flow",
      "source": "coingecko"
    },
    "RUNE": {
      "usd": 0.871866,
      "change_24h": -1.5935438079275894,
      "change_7d": 3.5207895057429948,
      "market_cap": 306274592,
      "id": "thorchain",
      "name": "THORChain",
      "source": "coingecko"
    },
    "FRAX": {
      "usd": 0.995983,
      "change_24h": -0.011517778480176847,
      "change_7d": 0.0015403686411092053,
      "market_cap": 290732721,
      "id": "frax",
      "name": "Legacy Frax Dollar",
      "source": "coingecko"
    },
    "MINA": {
      "usd": 0.09952,
      "change_24h": -7.027221683513561,
      "change_7d": -5.860094664451453,
      "market_cap": 125305049,
      "id": "mina-protocol",
      "name": "Mina Protocol",
      "source": "coingecko"
    },
    "BOME": {
      "usd": 0.00104226,
      "change_24h": -4.373046453748914,
      "change_7d": -1.8584445024229588,
      "market_cap": 71926175,
      "id": "book-of-meme",
      "name": "BOOK OF MEME",
      "source": "coingecko"
    },
    "GOAT": {
      "usd": 0.053391,
      "change_24h": -3.021223227564224,
      "change_7d": 3.5890941646170056,
      "market_cap": 53269003,
      "id": "goatseus-maximus",
      "name": "Goatseus Maximus",
      "source": "coingecko"
    },
    "STREAM": {
      "usd": 0.0326016,
      "change_24h": -7.453637231061366,
      "change_7d": -4.474639234639178,
      "market_cap": 4439699,
      "id": "streamflow",
      "name": "Streamflow",
      "source": "coingecko"
    },
    "CHILLGUY": {
      "usd": 0.00018631,
      "change_24h": -1.116985864034297,
      "change_7d": 8.164901092618994,
      "market_cap": 186375,
      "id": "just-a-chill-guy",
      "name": "Just a chill guy (ETH)",
      "source": "coingecko"
    },
    "FTM": {
      "usd": 0.253952,
      "change_24h": -8.125409998226099,
      "change_7d": 48.24150465596512,
      "market_cap": 0,
      "id": "fantom",
      "name": "Fantom",
      "source": "coingecko"
    },
    "MKR": {
      "usd": 1383.67,
      "change_24h": -1.4126135755956497,
      "change_7d": 0.5529035240403636,
      "market_cap": 0,
      "id": "maker",
      "name": "Maker",
      "source": "coingecko"
    }
  }
}