{
  "updated_at": "2025-11-01T18:51:58.536Z",
  "meta": {
    "included_ids": [
      "bitcoin",
      "ethereum",
      "tether",
      "binancecoin",
      "solana",
      "ripple",
      "usd-coin",
      "staked-ether",
      "cardano",
      "dogecoin",
      "avalanche-2",
      "tron",
      "shiba-inu",
      "wrapped-bitcoin",
      "polkadot",
      "chainlink",
      "bitcoin-cash",
      "uniswap",
      "litecoin",
      "internet-computer",
      "dai",
      "near",
      "ethereum-classic",
      "filecoin",
      "aptos",
      "leo-token",
      "stellar",
      "okb",
      "vechain",
      "render-token",
      "monero",
      "arbitrum",
      "fantom",
      "the-graph",
      "immutable-x",
      "maker",
      "kaspa",
      "gala",
      "optimism",
      "frax",
      "sei-network",
      "algorand",
      "flow",
      "thorchain",
      "conflux-token",
      "mina-protocol",
      "worldcoin-wld",
      "polygon-ecosystem-token",
      "bonk",
      "book-of-meme",
      "official-trump",
      "streamflow",
      "pudgy-penguins",
      "just-a-chill-guy",
      "goatseus-maximus"
    ],
    "wallet_resolved": [
      {
        "raw": "worldcoin",
        "resolved": "worldcoin-wld",
        "via": "override"
      },
      {
        "raw": "pol",
        "resolved": "polygon-ecosystem-token",
        "via": "override"
      },
      {
        "raw": "bonk",
        "resolved": "bonk",
        "via": "id"
      },
      {
        "raw": "bome",
        "resolved": "book-of-meme",
        "via": "override"
      },
      {
        "raw": "official-trump",
        "resolved": "official-trump",
        "via": "id"
      },
      {
        "raw": "streamflow",
        "resolved": "streamflow",
        "via": "id"
      },
      {
        "raw": "pengu",
        "resolved": "pudgy-penguins",
        "via": "override"
      },
      {
        "raw": "just-a-chill-guy",
        "resolved": "just-a-chill-guy",
        "via": "id"
      },
      {
        "raw": "goatseus-maximus",
        "resolved": "goatseus-maximus",
        "via": "id"
      },
      {
        "raw": "optimism",
        "resolved": "optimism",
        "via": "id"
      },
      {
        "raw": "solana",
        "resolved": "solana",
        "via": "id"
      },
      {
        "raw": "ripple",
        "resolved": "ripple",
        "via": "id"
      }
    ],
    "missing": [],
    "ambiguous": []
  },
  "assets": {
    "BTC": {
      "usd": 110268,
      "change_24h": 0.8778456091515662,
      "change_7d": -1.000313192467886,
      "market_cap": 2198823606872,
      "id": "bitcoin",
      "name": "Bitcoin",
      "source": "coingecko"
    },
    "ETH": {
      "usd": 3874.95,
      "change_24h": 0.7423287650336946,
      "change_7d": -1.4694900081830113,
      "market_cap": 467716424442,
      "id": "ethereum",
      "name": "Ethereum",
      "source": "coingecko"
    },
    "USDT": {
      "usd": 0.999897,
      "change_24h": 0.024661667337721776,
      "change_7d": -0.044147593510267244,
      "market_cap": 183433040747,
      "id": "tether",
      "name": "Tether",
      "source": "coingecko"
    },
    "BNB": {
      "usd": 1093.66,
      "change_24h": 1.2030418181748441,
      "change_7d": -1.5989159138149565,
      "market_cap": 150610245554,
      "id": "binancecoin",
      "name": "BNB",
      "source": "coingecko"
    },
    "XRP": {
      "usd": 2.5,
      "change_24h": -0.6459882625440033,
      "change_7d": -3.5150030742912604,
      "market_cap": 150228921124,
      "id": "ripple",
      "name": "XRP",
      "source": "coingecko"
    },
    "SOL": {
      "usd": 185.39,
      "change_24h": -0.15349687054571134,
      "change_7d": -3.358107848316405,
      "market_cap": 102423550231,
      "id": "solana",
      "name": "Solana",
      "source": "coingecko"
    },
    "USDC": {
      "usd": 0.999798,
      "change_24h": -0.001927496955026522,
      "change_7d": -0.010995559324449365,
      "market_cap": 75866267050,
      "id": "usd-coin",
      "name": "USDC",
      "source": "coingecko"
    },
    "STETH": {
      "usd": 3874.46,
      "change_24h": 0.7020950874238452,
      "change_7d": -1.5028824077952072,
      "market_cap": 33275998856,
      "id": "staked-ether",
      "name": "Lido Staked Ether",
      "source": "coingecko"
    },
    "DOGE": {
      "usd": 0.186997,
      "change_24h": 1.0371951718486225,
      "change_7d": -5.028964334469287,
      "market_cap": 28348518985,
      "id": "dogecoin",
      "name": "Dogecoin",
      "source": "coingecko"
    },
    "TRX": {
      "usd": 0.297376,
      "change_24h": 0.7950120800946602,
      "change_7d": -0.22998061708462414,
      "market_cap": 28144643139,
      "id": "tron",
      "name": "TRON",
      "source": "coingecko"
    },
    "ADA": {
      "usd": 0.610861,
      "change_24h": 1.065977642309458,
      "change_7d": -6.761062724072178,
      "market_cap": 22340909674,
      "id": "cardano",
      "name": "Cardano",
      "source": "coingecko"
    },
    "WBTC": {
      "usd": 110253,
      "change_24h": 0.6503886245785053,
      "change_7d": -0.9347465736725507,
      "market_cap": 13974017056,
      "id": "wrapped-bitcoin",
      "name": "Wrapped Bitcoin",
      "source": "coingecko"
    },
    "LINK": {
      "usd": 17.19,
      "change_24h": 1.1717682811776349,
      "change_7d": -4.532427069636829,
      "market_cap": 11962961075,
      "id": "chainlink",
      "name": "Chainlink",
      "source": "coingecko"
    },
    "BCH": {
      "usd": 554.45,
      "change_24h": 2.0138193137267675,
      "change_7d": 9.243160601903764,
      "market_cap": 11053510392,
      "id": "bitcoin-cash",
      "name": "Bitcoin Cash",
      "source": "coingecko"
    },
    "XLM": {
      "usd": 0.305832,
      "change_24h": 1.1461919920939307,
      "change_7d": -6.412379722330447,
      "market_cap": 9800478639,
      "id": "stellar",
      "name": "Stellar",
      "source": "coingecko"
    },
    "LEO": {
      "usd": 9.51,
      "change_24h": -0.5831854871659967,
      "change_7d": 5.724083074486358,
      "market_cap": 8774293319,
      "id": "leo-token",
      "name": "LEO Token",
      "source": "coingecko"
    },
    "AVAX": {
      "usd": 18.61,
      "change_24h": 3.5812617749316447,
      "change_7d": -4.565057801293182,
      "market_cap": 7940151282,
      "id": "avalanche-2",
      "name": "Avalanche",
      "source": "coingecko"
    },
    "LTC": {
      "usd": 99.42,
      "change_24h": 4.830654352278958,
      "change_7d": 3.4025663012284566,
      "market_cap": 7599386007,
      "id": "litecoin",
      "name": "Litecoin",
      "source": "coingecko"
    },
    "XMR": {
      "usd": 341.07,
      "change_24h": 4.122253492848156,
      "change_7d": 1.8388322677531952,
      "market_cap": 6283062308,
      "id": "monero",
      "name": "Monero",
      "source": "coingecko"
    },
    "SHIB": {
      "usd": 0.00001017,
      "change_24h": 2.2685832049386088,
      "change_7d": 0.22769353174162993,
      "market_cap": 5994239568,
      "id": "shiba-inu",
      "name": "Shiba Inu",
      "source": "coingecko"
    },
    "DAI": {
      "usd": 0.999746,
      "change_24h": 0.24347989052378294,
      "change_7d": 0.010050511922122541,
      "market_cap": 4626574208,
      "id": "dai",
      "name": "Dai",
      "source": "coingecko"
    },
    "DOT": {
      "usd": 2.95,
      "change_24h": 3.1723208493339983,
      "change_7d": -3.77644096812189,
      "market_cap": 4487321732,
      "id": "polkadot",
      "name": "Polkadot",
      "source": "coingecko"
    },
    "UNI": {
      "usd": 5.84,
      "change_24h": 2.395577911475044,
      "change_7d": -6.092306850633906,
      "market_cap": 3507550970,
      "id": "uniswap",
      "name": "Uniswap",
      "source": "coingecko"
    },
    "OKB": {
      "usd": 143.25,
      "change_24h": 0.917318297771624,
      "change_7d": -13.531069968964129,
      "market_cap": 3010561879,
      "id": "okb",
      "name": "OKB",
      "source": "coingecko"
    },
    "NEAR": {
      "usd": 2.16,
      "change_24h": 3.05790528332043,
      "change_7d": -5.334290050456334,
      "market_cap": 2761479962,
      "id": "near",
      "name": "NEAR Protocol",
      "source": "coingecko"
    },
    "ETC": {
      "usd": 16.3,
      "change_24h": 3.194687259216786,
      "change_7d": 2.054288721202559,
      "market_cap": 2513691965,
      "id": "ethereum-classic",
      "name": "Ethereum Classic",
      "source": "coingecko"
    },
    "APT": {
      "usd": 3.32,
      "change_24h": 2.6494670937850757,
      "change_7d": 0.7630066008624456,
      "market_cap": 2388581785,
      "id": "aptos",
      "name": "Aptos",
      "source": "coingecko"
    },
    "POL": {
      "usd": 0.190888,
      "change_24h": 5.295048993465324,
      "change_7d": -2.1706633580921593,
      "market_cap": 2009788385,
      "id": "polygon-ecosystem-token",
      "name": "POL (ex-MATIC)",
      "source": "coingecko"
    },
    "WLD": {
      "usd": 0.882155,
      "change_24h": 10.901158555396254,
      "change_7d": -0.10503886680238882,
      "market_cap": 2003458477,
      "id": "worldcoin-wld",
      "name": "Worldcoin",
      "source": "coingecko"
    },
    "ICP": {
      "usd": 3.45,
      "change_24h": 18.373490691699747,
      "change_7d": 10.949572539512669,
      "market_cap": 1855161133,
      "id": "internet-computer",
      "name": "Internet Computer",
      "source": "coingecko"
    },
    "ARB": {
      "usd": 0.30624,
      "change_24h": 5.072811568072275,
      "change_7d": -3.9552061667163185,
      "market_cap": 1687504552,
      "id": "arbitrum",
      "name": "Arbitrum",
      "source": "coingecko"
    },
    "TRUMP": {
      "usd": 7.94,
      "change_24h": 0.3114101044830005,
      "change_7d": 33.16144567634181,
      "market_cap": 1586268115,
      "id": "official-trump",
      "name": "Official Trump",
      "source": "coingecko"
    },
    "ALGO": {
      "usd": 0.179679,
      "change_24h": 2.9072721227595815,
      "change_7d": -2.795523802806294,
      "market_cap": 1578939375,
      "id": "algorand",
      "name": "Algorand",
      "source": "coingecko"
    },
    "KAS": {
      "usd": 0.053424,
      "change_24h": 1.904407243808717,
      "change_7d": -2.0406562738586533,
      "market_cap": 1430812233,
      "id": "kaspa",
      "name": "Kaspa",
      "source": "coingecko"
    },
    "VET": {
      "usd": 0.01621418,
      "change_24h": 4.901679366066115,
      "change_7d": -6.143444927983756,
      "market_cap": 1393795387,
      "id": "vechain",
      "name": "VeChain",
      "source": "coingecko"
    },
    "SEI": {
      "usd": 0.195018,
      "change_24h": 2.5441739226158595,
      "change_7d": -1.7098997814175443,
      "market_cap": 1218581615,
      "id": "sei-network",
      "name": "Sei",
      "source": "coingecko"
    },
    "RENDER": {
      "usd": 2.34,
      "change_24h": 5.5018898097429005,
      "change_7d": -5.165102813567078,
      "market_cap": 1210980595,
      "id": "render-token",
      "name": "Render",
      "source": "coingecko"
    },
    "FIL": {
      "usd": 1.68,
      "change_24h": 12.818880471319025,
      "change_7d": 7.642934919632055,
      "market_cap": 1185246340,
      "id": "filecoin",
      "name": "Filecoin",
      "source": "coingecko"
    },
    "PENGU": {
      "usd": 0.01828941,
      "change_24h": 2.760787642743031,
      "change_7d": -14.408008566984442,
      "market_cap": 1149707715,
      "id": "pudgy-penguins",
      "name": "Pudgy Penguins",
      "source": "coingecko"
    },
    "BONK": {
      "usd": 0.00001424,
      "change_24h": 2.2779654477433633,
      "change_7d": -3.649898110329966,
      "market_cap": 1102671865,
      "id": "bonk",
      "name": "Bonk",
      "source": "coingecko"
    },
    "IMX": {
      "usd": 0.513309,
      "change_24h": 7.009801126176189,
      "change_7d": -4.525652325464027,
      "market_cap": 1008588105,
      "id": "immutable-x",
      "name": "Immutable",
      "source": "coingecko"
    },
    "OP": {
      "usd": 0.415578,
      "change_24h": 5.588765827993575,
      "change_7d": -7.025127094937932,
      "market_cap": 788258168,
      "id": "optimism",
      "name": "Optimism",
      "source": "coingecko"
    },
    "GRT": {
      "usd": 0.064089,
      "change_24h": 4.848556534420755,
      "change_7d": -0.910603763399059,
      "market_cap": 676237809,
      "id": "the-graph",
      "name": "The Graph",
      "source": "coingecko"
    },
    "CFX": {
      "usd": 0.103479,
      "change_24h": 1.978238667141343,
      "change_7d": -6.39996715526501,
      "market_cap": 532912087,
      "id": "conflux-token",
      "name": "Conflux",
      "source": "coingecko"
    },
    "GALA": {
      "usd": 0.01037598,
      "change_24h": 3.9880626351837103,
      "change_7d": -6.724094167175711,
      "market_cap": 481916091,
      "id": "gala",
      "name": "GALA",
      "source": "coingecko"
    },
    "FLOW": {
      "usd": 0.265842,
      "change_24h": 2.0693539774582015,
      "change_7d": -2.19802088256951,
      "market_cap": 430349427,
      "id": "flow",
      "name": "Flow",
      "source": "coingecko"
    },
    "RUNE": {
      "usd": 0.860406,
      "change_24h": 2.5679984766453834,
      "change_7d": 0.3800311204314138,
      "market_cap": 302138235,
      "id": "thorchain",
      "name": "THORChain",
      "source": "coingecko"
    },
    "FRAX": {
      "usd": 0.995421,
      "change_24h": 0.0054527619916859725,
      "change_7d": -0.03748466470562284,
      "market_cap": 290677592,
      "id": "frax",
      "name": "Legacy Frax Dollar",
      "source": "coingecko"
    },
    "MINA": {
      "usd": 0.120619,
      "change_24h": 27.90902312225379,
      "change_7d": 14.661564563443749,
      "market_cap": 151813961,
      "id": "mina-protocol",
      "name": "Mina Protocol",
      "source": "coingecko"
    },
    "BOME": {
      "usd": 0.00100774,
      "change_24h": 4.469404058446642,
      "change_7d": -6.806939393149225,
      "market_cap": 69403339,
      "id": "book-of-meme",
      "name": "BOOK OF MEME",
      "source": "coingecko"
    },
    "GOAT": {
      "usd": 0.053719,
      "change_24h": 7.89881555914257,
      "change_7d": -2.255809224853966,
      "market_cap": 53768876,
      "id": "goatseus-maximus",
      "name": "Goatseus Maximus",
      "source": "coingecko"
    },
    "STREAM": {
      "usd": 0.02932472,
      "change_24h": -0.11511371469841998,
      "change_7d": -19.215510721533253,
      "market_cap": 3993591,
      "id": "streamflow",
      "name": "Streamflow",
      "source": "coingecko"
    },
    "CHILLGUY": {
      "usd": 0.00018289,
      "change_24h": 0.21547050410927532,
      "change_7d": 0.7247086762999473,
      "market_cap": 182885,
      "id": "just-a-chill-guy",
      "name": "Just a chill guy (ETH)",
      "source": "coingecko"
    },
    "FTM": {
      "usd": 0.15699,
      "change_24h": 8.325792814342154,
      "change_7d": -6.878018639352165,
      "market_cap": 0,
      "id": "fantom",
      "name": "Fantom",
      "source": "coingecko"
    },
    "MKR": {
      "usd": 1330.61,
      "change_24h": 0.44003001270325426,
      "change_7d": -5.172139267874852,
      "market_cap": 0,
      "id": "maker",
      "name": "Maker",
      "source": "coingecko"
    }
  }
}