{
  "updated_at": "2025-11-01T16:54:11.031Z",
  "meta": {
    "included_ids": [
      "bitcoin",
      "ethereum",
      "tether",
      "binancecoin",
      "solana",
      "ripple",
      "usd-coin",
      "staked-ether",
      "cardano",
      "dogecoin",
      "avalanche-2",
      "tron",
      "shiba-inu",
      "wrapped-bitcoin",
      "polkadot",
      "chainlink",
      "bitcoin-cash",
      "uniswap",
      "litecoin",
      "internet-computer",
      "dai",
      "near",
      "ethereum-classic",
      "filecoin",
      "aptos",
      "leo-token",
      "stellar",
      "okb",
      "vechain",
      "render-token",
      "monero",
      "arbitrum",
      "fantom",
      "the-graph",
      "immutable-x",
      "maker",
      "kaspa",
      "gala",
      "optimism",
      "frax",
      "sei-network",
      "algorand",
      "flow",
      "thorchain",
      "conflux-token",
      "mina-protocol",
      "worldcoin-wld",
      "polygon-ecosystem-token",
      "bonk",
      "book-of-meme",
      "official-trump",
      "streamflow",
      "pudgy-penguins",
      "just-a-chill-guy",
      "goatseus-maximus"
    ],
    "wallet_resolved": [
      {
        "raw": "worldcoin",
        "resolved": "worldcoin-wld",
        "via": "override"
      },
      {
        "raw": "pol",
        "resolved": "polygon-ecosystem-token",
        "via": "override"
      },
      {
        "raw": "bonk",
        "resolved": "bonk",
        "via": "id"
      },
      {
        "raw": "bome",
        "resolved": "book-of-meme",
        "via": "override"
      },
      {
        "raw": "official-trump",
        "resolved": "official-trump",
        "via": "id"
      },
      {
        "raw": "streamflow",
        "resolved": "streamflow",
        "via": "id"
      },
      {
        "raw": "pengu",
        "resolved": "pudgy-penguins",
        "via": "override"
      },
      {
        "raw": "just-a-chill-guy",
        "resolved": "just-a-chill-guy",
        "via": "id"
      },
      {
        "raw": "goatseus-maximus",
        "resolved": "goatseus-maximus",
        "via": "id"
      },
      {
        "raw": "optimism",
        "resolved": "optimism",
        "via": "id"
      },
      {
        "raw": "solana",
        "resolved": "solana",
        "via": "id"
      },
      {
        "raw": "ripple",
        "resolved": "ripple",
        "via": "id"
      }
    ],
    "missing": [],
    "ambiguous": []
  },
  "assets": {
    "BTC": {
      "usd": 110491,
      "change_24h": 0.9689545872883891,
      "change_7d": -0.8644135840943356,
      "market_cap": 2202750155344,
      "id": "bitcoin",
      "name": "Bitcoin",
      "source": "coingecko"
    },
    "ETH": {
      "usd": 3897.87,
      "change_24h": 1.749672176341118,
      "change_7d": -0.8515987727790916,
      "market_cap": 470292980777,
      "id": "ethereum",
      "name": "Ethereum",
      "source": "coingecko"
    },
    "USDT": {
      "usd": 0.999952,
      "change_24h": 0.028509747197564845,
      "change_7d": -0.04091427708354635,
      "market_cap": 183447301001,
      "id": "tether",
      "name": "Tether",
      "source": "coingecko"
    },
    "XRP": {
      "usd": 2.51,
      "change_24h": -0.1288865069202108,
      "change_7d": -3.577429833593837,
      "market_cap": 150814820350,
      "id": "ripple",
      "name": "XRP",
      "source": "coingecko"
    },
    "BNB": {
      "usd": 1093.74,
      "change_24h": 1.5634512657968582,
      "change_7d": -1.3859895822916553,
      "market_cap": 150647395936,
      "id": "binancecoin",
      "name": "BNB",
      "source": "coingecko"
    },
    "SOL": {
      "usd": 186.83,
      "change_24h": 0.5491916818245888,
      "change_7d": -3.0227193940041754,
      "market_cap": 103221325568,
      "id": "solana",
      "name": "Solana",
      "source": "coingecko"
    },
    "USDC": {
      "usd": 0.999829,
      "change_24h": 0.0119738883540689,
      "change_7d": 0.0019770554770556486,
      "market_cap": 75877629744,
      "id": "usd-coin",
      "name": "USDC",
      "source": "coingecko"
    },
    "STETH": {
      "usd": 3896.92,
      "change_24h": 1.677960288327708,
      "change_7d": -0.8662978276127697,
      "market_cap": 33452177955,
      "id": "staked-ether",
      "name": "Lido Staked Ether",
      "source": "coingecko"
    },
    "DOGE": {
      "usd": 0.187637,
      "change_24h": 1.8457479651437372,
      "change_7d": -4.46707421559988,
      "market_cap": 28430432759,
      "id": "dogecoin",
      "name": "Dogecoin",
      "source": "coingecko"
    },
    "TRX": {
      "usd": 0.297412,
      "change_24h": 0.7670715069150971,
      "change_7d": -0.14717460261096804,
      "market_cap": 28154549609,
      "id": "tron",
      "name": "TRON",
      "source": "coingecko"
    },
    "ADA": {
      "usd": 0.613783,
      "change_24h": 1.2485653395899479,
      "change_7d": -5.959995214637879,
      "market_cap": 22443123038,
      "id": "cardano",
      "name": "Cardano",
      "source": "coingecko"
    },
    "WBTC": {
      "usd": 110364,
      "change_24h": 1.199150054461203,
      "change_7d": -1.1469961937352926,
      "market_cap": 13989025064,
      "id": "wrapped-bitcoin",
      "name": "Wrapped Bitcoin",
      "source": "coingecko"
    },
    "LINK": {
      "usd": 17.3,
      "change_24h": 1.5869608801622557,
      "change_7d": -3.9515382662383276,
      "market_cap": 12053637520,
      "id": "chainlink",
      "name": "Chainlink",
      "source": "coingecko"
    },
    "BCH": {
      "usd": 556.5,
      "change_24h": 1.063763901263561,
      "change_7d": 9.763898062485174,
      "market_cap": 11097778283,
      "id": "bitcoin-cash",
      "name": "Bitcoin Cash",
      "source": "coingecko"
    },
    "XLM": {
      "usd": 0.306933,
      "change_24h": 1.1892873548202165,
      "change_7d": -6.788441902552076,
      "market_cap": 9829920727,
      "id": "stellar",
      "name": "Stellar",
      "source": "coingecko"
    },
    "LEO": {
      "usd": 9.55,
      "change_24h": -0.20921529623205296,
      "change_7d": 6.078766054826393,
      "market_cap": 8805717976,
      "id": "leo-token",
      "name": "LEO Token",
      "source": "coingecko"
    },
    "AVAX": {
      "usd": 18.7,
      "change_24h": 3.755392850571029,
      "change_7d": -4.266767478158825,
      "market_cap": 7977433573,
      "id": "avalanche-2",
      "name": "Avalanche",
      "source": "coingecko"
    },
    "LTC": {
      "usd": 99.22,
      "change_24h": 4.50729008495289,
      "change_7d": 3.189612782752391,
      "market_cap": 7580552599,
      "id": "litecoin",
      "name": "Litecoin",
      "source": "coingecko"
    },
    "XMR": {
      "usd": 342.47,
      "change_24h": 6.298371118308964,
      "change_7d": 2.714515697342848,
      "market_cap": 6311349543,
      "id": "monero",
      "name": "Monero",
      "source": "coingecko"
    },
    "SHIB": {
      "usd": 0.00001017,
      "change_24h": 2.567491903904072,
      "change_7d": 0.3180976563241897,
      "market_cap": 5995399112,
      "id": "shiba-inu",
      "name": "Shiba Inu",
      "source": "coingecko"
    },
    "DAI": {
      "usd": 0.999682,
      "change_24h": 0.04574742451460344,
      "change_7d": -0.05678386300887411,
      "market_cap": 4606748951,
      "id": "dai",
      "name": "Dai",
      "source": "coingecko"
    },
    "DOT": {
      "usd": 2.96,
      "change_24h": 3.3553534399064326,
      "change_7d": -3.353047180371422,
      "market_cap": 4508010271,
      "id": "polkadot",
      "name": "Polkadot",
      "source": "coingecko"
    },
    "UNI": {
      "usd": 5.89,
      "change_24h": 3.645100661637385,
      "change_7d": -4.768993165712669,
      "market_cap": 3535919609,
      "id": "uniswap",
      "name": "Uniswap",
      "source": "coingecko"
    },
    "OKB": {
      "usd": 141.9,
      "change_24h": -1.8732332449608553,
      "change_7d": -14.974649184306832,
      "market_cap": 2979702194,
      "id": "okb",
      "name": "OKB",
      "source": "coingecko"
    },
    "NEAR": {
      "usd": 2.17,
      "change_24h": 3.4831664325071072,
      "change_7d": -4.600068028111639,
      "market_cap": 2776227637,
      "id": "near",
      "name": "NEAR Protocol",
      "source": "coingecko"
    },
    "ETC": {
      "usd": 16.48,
      "change_24h": 3.6171880255016857,
      "change_7d": 3.572404457292693,
      "market_cap": 2539220446,
      "id": "ethereum-classic",
      "name": "Ethereum Classic",
      "source": "coingecko"
    },
    "APT": {
      "usd": 3.32,
      "change_24h": 2.2967828310417127,
      "change_7d": 0.6675665716467575,
      "market_cap": 2385755796,
      "id": "aptos",
      "name": "Aptos",
      "source": "coingecko"
    },
    "POL": {
      "usd": 0.191507,
      "change_24h": 3.357065988658546,
      "change_7d": -1.786121075520082,
      "market_cap": 2016493701,
      "id": "polygon-ecosystem-token",
      "name": "POL (ex-MATIC)",
      "source": "coingecko"
    },
    "WLD": {
      "usd": 0.876826,
      "change_24h": 10.286501294735917,
      "change_7d": -0.3936370874856842,
      "market_cap": 1990469350,
      "id": "worldcoin-wld",
      "name": "Worldcoin",
      "source": "coingecko"
    },
    "ICP": {
      "usd": 3.41,
      "change_24h": 17.04329224327757,
      "change_7d": 9.635827912434843,
      "market_cap": 1838271939,
      "id": "internet-computer",
      "name": "Internet Computer",
      "source": "coingecko"
    },
    "ARB": {
      "usd": 0.307286,
      "change_24h": 5.631895298894448,
      "change_7d": -3.686863574050711,
      "market_cap": 1691537647,
      "id": "arbitrum",
      "name": "Arbitrum",
      "source": "coingecko"
    },
    "TRUMP": {
      "usd": 7.94,
      "change_24h": -0.9542685992439212,
      "change_7d": 33.170606573324214,
      "market_cap": 1585320089,
      "id": "official-trump",
      "name": "Official Trump",
      "source": "coingecko"
    },
    "ALGO": {
      "usd": 0.179314,
      "change_24h": 2.2955272679770875,
      "change_7d": -3.2114746480906518,
      "market_cap": 1572109991,
      "id": "algorand",
      "name": "Algorand",
      "source": "coingecko"
    },
    "KAS": {
      "usd": 0.053493,
      "change_24h": 2.15457350932692,
      "change_7d": -2.3425499711560622,
      "market_cap": 1432395690,
      "id": "kaspa",
      "name": "Kaspa",
      "source": "coingecko"
    },
    "VET": {
      "usd": 0.01624603,
      "change_24h": 4.541500842060053,
      "change_7d": -5.901612070191714,
      "market_cap": 1397058111,
      "id": "vechain",
      "name": "VeChain",
      "source": "coingecko"
    },
    "SEI": {
      "usd": 0.195027,
      "change_24h": 1.7445080634561498,
      "change_7d": -1.2788599153964517,
      "market_cap": 1218092469,
      "id": "sei-network",
      "name": "Sei",
      "source": "coingecko"
    },
    "RENDER": {
      "usd": 2.33,
      "change_24h": 4.231969358429357,
      "change_7d": -5.152133193415521,
      "market_cap": 1208433318,
      "id": "render-token",
      "name": "Render",
      "source": "coingecko"
    },
    "FIL": {
      "usd": 1.69,
      "change_24h": 14.089815547033652,
      "change_7d": 8.205542755539245,
      "market_cap": 1194734692,
      "id": "filecoin",
      "name": "Filecoin",
      "source": "coingecko"
    },
    "PENGU": {
      "usd": 0.0182876,
      "change_24h": 0.1073153859330731,
      "change_7d": -13.224333677018477,
      "market_cap": 1149874379,
      "id": "pudgy-penguins",
      "name": "Pudgy Penguins",
      "source": "coingecko"
    },
    "BONK": {
      "usd": 0.00001431,
      "change_24h": 2.5130680668915764,
      "change_7d": -3.191640360042862,
      "market_cap": 1107578120,
      "id": "bonk",
      "name": "Bonk",
      "source": "coingecko"
    },
    "IMX": {
      "usd": 0.514051,
      "change_24h": 7.204683492504188,
      "change_7d": -4.0583999888680795,
      "market_cap": 1009277320,
      "id": "immutable-x",
      "name": "Immutable",
      "source": "coingecko"
    },
    "OP": {
      "usd": 0.413863,
      "change_24h": 4.249918820480787,
      "change_7d": -7.270211158595971,
      "market_cap": 784115734,
      "id": "optimism",
      "name": "Optimism",
      "source": "coingecko"
    },
    "GRT": {
      "usd": 0.064335,
      "change_24h": 4.985816216576809,
      "change_7d": -0.3875744502925724,
      "market_cap": 680196983,
      "id": "the-graph",
      "name": "The Graph",
      "source": "coingecko"
    },
    "CFX": {
      "usd": 0.103378,
      "change_24h": 2.098411818937413,
      "change_7d": -6.436395278582715,
      "market_cap": 532474603,
      "id": "conflux-token",
      "name": "Conflux",
      "source": "coingecko"
    },
    "GALA": {
      "usd": 0.01042057,
      "change_24h": 4.139722565592485,
      "change_7d": -6.766503852308066,
      "market_cap": 483984826,
      "id": "gala",
      "name": "GALA",
      "source": "coingecko"
    },
    "FLOW": {
      "usd": 0.265434,
      "change_24h": 1.0288440639537133,
      "change_7d": -2.5628880414057775,
      "market_cap": 429606311,
      "id": "flow",
      "name": "Flow",
      "source": "coingecko"
    },
    "RUNE": {
      "usd": 0.861166,
      "change_24h": 2.372250383454524,
      "change_7d": 0.2249969533145839,
      "market_cap": 302331209,
      "id": "thorchain",
      "name": "THORChain",
      "source": "coingecko"
    },
    "FRAX": {
      "usd": 0.995302,
      "change_24h": -0.03227659358427816,
      "change_7d": -0.11560824936024644,
      "market_cap": 290683578,
      "id": "frax",
      "name": "Legacy Frax Dollar",
      "source": "coingecko"
    },
    "MINA": {
      "usd": 0.111926,
      "change_24h": 18.782057644004606,
      "change_7d": 6.385929909925481,
      "market_cap": 139783011,
      "id": "mina-protocol",
      "name": "Mina Protocol",
      "source": "coingecko"
    },
    "BOME": {
      "usd": 0.00100707,
      "change_24h": 3.718908232562984,
      "change_7d": -6.912946933590312,
      "market_cap": 69340028,
      "id": "book-of-meme",
      "name": "BOOK OF MEME",
      "source": "coingecko"
    },
    "GOAT": {
      "usd": 0.053951,
      "change_24h": 7.678179390627045,
      "change_7d": -3.277643972718811,
      "market_cap": 53961064,
      "id": "goatseus-maximus",
      "name": "Goatseus Maximus",
      "source": "coingecko"
    },
    "STREAM": {
      "usd": 0.02939209,
      "change_24h": -0.14259390419618148,
      "change_7d": -23.98040173504505,
      "market_cap": 4002729,
      "id": "streamflow",
      "name": "Streamflow",
      "source": "coingecko"
    },
    "CHILLGUY": {
      "usd": 0.0001838,
      "change_24h": 1.263150252450694,
      "change_7d": 1.0562190869672912,
      "market_cap": 183798,
      "id": "just-a-chill-guy",
      "name": "Just a chill guy (ETH)",
      "source": "coingecko"
    },
    "FTM": {
      "usd": 0.157354,
      "change_24h": 6.9671253588653395,
      "change_7d": -5.928460183547856,
      "market_cap": 0,
      "id": "fantom",
      "name": "Fantom",
      "source": "coingecko"
    },
    "MKR": {
      "usd": 1339.37,
      "change_24h": 0.517135210680646,
      "change_7d": -4.803105889115173,
      "market_cap": 0,
      "id": "maker",
      "name": "Maker",
      "source": "coingecko"
    }
  }
}