{
  "updated_at": "2025-10-31T06:21:19.202Z",
  "meta": {
    "included_ids": [
      "bitcoin",
      "ethereum",
      "tether",
      "binancecoin",
      "solana",
      "ripple",
      "usd-coin",
      "staked-ether",
      "cardano",
      "dogecoin",
      "avalanche-2",
      "tron",
      "shiba-inu",
      "wrapped-bitcoin",
      "polkadot",
      "chainlink",
      "bitcoin-cash",
      "uniswap",
      "litecoin",
      "internet-computer",
      "dai",
      "near",
      "ethereum-classic",
      "filecoin",
      "aptos",
      "leo-token",
      "stellar",
      "okb",
      "vechain",
      "render-token",
      "monero",
      "arbitrum",
      "fantom",
      "the-graph",
      "immutable-x",
      "maker",
      "kaspa",
      "gala",
      "optimism",
      "frax",
      "sei-network",
      "algorand",
      "flow",
      "thorchain",
      "conflux-token",
      "mina-protocol",
      "worldcoin-wld",
      "polygon-ecosystem-token",
      "bonk",
      "book-of-meme",
      "official-trump",
      "streamflow",
      "pudgy-penguins",
      "just-a-chill-guy",
      "goatseus-maximus"
    ],
    "wallet_resolved": [
      {
        "raw": "worldcoin",
        "resolved": "worldcoin-wld",
        "via": "override"
      },
      {
        "raw": "pol",
        "resolved": "polygon-ecosystem-token",
        "via": "override"
      },
      {
        "raw": "bonk",
        "resolved": "bonk",
        "via": "id"
      },
      {
        "raw": "bome",
        "resolved": "book-of-meme",
        "via": "override"
      },
      {
        "raw": "official-trump",
        "resolved": "official-trump",
        "via": "id"
      },
      {
        "raw": "streamflow",
        "resolved": "streamflow",
        "via": "id"
      },
      {
        "raw": "pengu",
        "resolved": "pudgy-penguins",
        "via": "override"
      },
      {
        "raw": "just-a-chill-guy",
        "resolved": "just-a-chill-guy",
        "via": "id"
      },
      {
        "raw": "goatseus-maximus",
        "resolved": "goatseus-maximus",
        "via": "id"
      },
      {
        "raw": "optimism",
        "resolved": "optimism",
        "via": "id"
      },
      {
        "raw": "solana",
        "resolved": "solana",
        "via": "id"
      },
      {
        "raw": "ripple",
        "resolved": "ripple",
        "via": "id"
      }
    ],
    "missing": [],
    "ambiguous": []
  },
  "assets": {
    "BTC": {
      "usd": 109635,
      "change_24h": -0.4530630650329613,
      "change_7d": -1.490718274016572,
      "market_cap": 2186538440301,
      "id": "bitcoin",
      "name": "Bitcoin",
      "source": "coingecko"
    },
    "ETH": {
      "usd": 3829.8,
      "change_24h": -1.9439129767583871,
      "change_7d": -3.6906846533255067,
      "market_cap": 462834273145,
      "id": "ethereum",
      "name": "Ethereum",
      "source": "coingecko"
    },
    "USDT": {
      "usd": 1,
      "change_24h": -0.028108242350865897,
      "change_7d": -0.03945590813310419,
      "market_cap": 183403817449,
      "id": "tether",
      "name": "Tether",
      "source": "coingecko"
    },
    "BNB": {
      "usd": 1092.16,
      "change_24h": -1.6449048143261673,
      "change_7d": -4.247514081557411,
      "market_cap": 150623109225,
      "id": "binancecoin",
      "name": "BNB",
      "source": "coingecko"
    },
    "XRP": {
      "usd": 2.48,
      "change_24h": -3.0958232728026136,
      "change_7d": 1.6559207246723786,
      "market_cap": 149000471623,
      "id": "ripple",
      "name": "XRP",
      "source": "coingecko"
    },
    "SOL": {
      "usd": 185.16,
      "change_24h": -4.648797394859988,
      "change_7d": -4.5961689043626,
      "market_cap": 101859912580,
      "id": "solana",
      "name": "Solana",
      "source": "coingecko"
    },
    "USDC": {
      "usd": 0.999731,
      "change_24h": -0.013024159876472286,
      "change_7d": -0.01112797275215693,
      "market_cap": 75838144632,
      "id": "usd-coin",
      "name": "USDC",
      "source": "coingecko"
    },
    "STETH": {
      "usd": 3832.87,
      "change_24h": -1.814462934242299,
      "change_7d": -3.6883183741648375,
      "market_cap": 32956728202,
      "id": "staked-ether",
      "name": "Lido Staked Ether",
      "source": "coingecko"
    },
    "DOGE": {
      "usd": 0.184563,
      "change_24h": -3.1754513088287917,
      "change_7d": -6.82065013212689,
      "market_cap": 27981462167,
      "id": "dogecoin",
      "name": "Dogecoin",
      "source": "coingecko"
    },
    "TRX": {
      "usd": 0.29451,
      "change_24h": -0.3684437844532281,
      "change_7d": -6.174619892630461,
      "market_cap": 27882421060,
      "id": "tron",
      "name": "TRON",
      "source": "coingecko"
    },
    "ADA": {
      "usd": 0.61147,
      "change_24h": -4.007358244726126,
      "change_7d": -6.260003047823837,
      "market_cap": 22391970870,
      "id": "cardano",
      "name": "Cardano",
      "source": "coingecko"
    },
    "WBTC": {
      "usd": 109772,
      "change_24h": -0.4621615598523891,
      "change_7d": -1.2659887345522267,
      "market_cap": 13915429662,
      "id": "wrapped-bitcoin",
      "name": "Wrapped Bitcoin",
      "source": "coingecko"
    },
    "LINK": {
      "usd": 17.19,
      "change_24h": -4.666660694199104,
      "change_7d": -2.894834754301256,
      "market_cap": 11977927958,
      "id": "chainlink",
      "name": "Chainlink",
      "source": "coingecko"
    },
    "BCH": {
      "usd": 549.04,
      "change_24h": -2.8751101767963174,
      "change_7d": 12.600054623653396,
      "market_cap": 10936273510,
      "id": "bitcoin-cash",
      "name": "Bitcoin Cash",
      "source": "coingecko"
    },
    "XLM": {
      "usd": 0.301874,
      "change_24h": -3.940110390298896,
      "change_7d": -4.6851309801976555,
      "market_cap": 9672911475,
      "id": "stellar",
      "name": "Stellar",
      "source": "coingecko"
    },
    "LEO": {
      "usd": 9.6,
      "change_24h": -0.18860756883528623,
      "change_7d": 7.010949768556071,
      "market_cap": 8853890603,
      "id": "leo-token",
      "name": "LEO Token",
      "source": "coingecko"
    },
    "AVAX": {
      "usd": 18.31,
      "change_24h": -6.45822141582197,
      "change_7d": -6.691698879408929,
      "market_cap": 7812994279,
      "id": "avalanche-2",
      "name": "Avalanche",
      "source": "coingecko"
    },
    "LTC": {
      "usd": 93.99,
      "change_24h": -3.9371873706211695,
      "change_7d": -1.7961692282637098,
      "market_cap": 7190601635,
      "id": "litecoin",
      "name": "Litecoin",
      "source": "coingecko"
    },
    "XMR": {
      "usd": 320.28,
      "change_24h": -2.641666871899063,
      "change_7d": -1.3810992443341321,
      "market_cap": 5905360070,
      "id": "monero",
      "name": "Monero",
      "source": "coingecko"
    },
    "SHIB": {
      "usd": 0.00000983,
      "change_24h": -2.369914128865142,
      "change_7d": -3.5410266749079664,
      "market_cap": 5804219110,
      "id": "shiba-inu",
      "name": "Shiba Inu",
      "source": "coingecko"
    },
    "DAI": {
      "usd": 1,
      "change_24h": 0.09832628224629424,
      "change_7d": 0.19828493124051527,
      "market_cap": 4640885276,
      "id": "dai",
      "name": "Dai",
      "source": "coingecko"
    },
    "DOT": {
      "usd": 2.9,
      "change_24h": -4.53951552763052,
      "change_7d": -5.014967797720062,
      "market_cap": 4421699723,
      "id": "polkadot",
      "name": "Polkadot",
      "source": "coingecko"
    },
    "UNI": {
      "usd": 5.91,
      "change_24h": -2.6019872288049823,
      "change_7d": -7.794120689030171,
      "market_cap": 3545701136,
      "id": "uniswap",
      "name": "Uniswap",
      "source": "coingecko"
    },
    "OKB": {
      "usd": 148.33,
      "change_24h": -5.329010650711618,
      "change_7d": -10.117434371843675,
      "market_cap": 3115176506,
      "id": "okb",
      "name": "OKB",
      "source": "coingecko"
    },
    "NEAR": {
      "usd": 2.11,
      "change_24h": -5.495123123126373,
      "change_7d": -5.9636942197604235,
      "market_cap": 2705366101,
      "id": "near",
      "name": "NEAR Protocol",
      "source": "coingecko"
    },
    "ETC": {
      "usd": 15.61,
      "change_24h": -1.422015053786415,
      "change_7d": -1.7607406442347946,
      "market_cap": 2405950841,
      "id": "ethereum-classic",
      "name": "Ethereum Classic",
      "source": "coingecko"
    },
    "APT": {
      "usd": 3.25,
      "change_24h": -3.1990348254687864,
      "change_7d": -0.21702811179569081,
      "market_cap": 2339423941,
      "id": "aptos",
      "name": "Aptos",
      "source": "coingecko"
    },
    "POL": {
      "usd": 0.186821,
      "change_24h": -3.3599917409649476,
      "change_7d": -4.1259007916603005,
      "market_cap": 1967776418,
      "id": "polygon-ecosystem-token",
      "name": "POL (ex-MATIC)",
      "source": "coingecko"
    },
    "WLD": {
      "usd": 0.806657,
      "change_24h": -4.482462232595991,
      "change_7d": -7.987962177191116,
      "market_cap": 1831883340,
      "id": "worldcoin-wld",
      "name": "Worldcoin",
      "source": "coingecko"
    },
    "ARB": {
      "usd": 0.292465,
      "change_24h": -6.619905483861239,
      "change_7d": -8.149271456734207,
      "market_cap": 1611524799,
      "id": "arbitrum",
      "name": "Arbitrum",
      "source": "coingecko"
    },
    "TRUMP": {
      "usd": 8.03,
      "change_24h": -1.2326074334727848,
      "change_7d": 35.551403114758195,
      "market_cap": 1605182478,
      "id": "official-trump",
      "name": "Official Trump",
      "source": "coingecko"
    },
    "ICP": {
      "usd": 2.91,
      "change_24h": -3.574935644071378,
      "change_7d": -6.418958846429858,
      "market_cap": 1570412771,
      "id": "internet-computer",
      "name": "Internet Computer",
      "source": "coingecko"
    },
    "ALGO": {
      "usd": 0.175707,
      "change_24h": -4.572973242827044,
      "change_7d": -4.600633057549045,
      "market_cap": 1546995868,
      "id": "algorand",
      "name": "Algorand",
      "source": "coingecko"
    },
    "KAS": {
      "usd": 0.053911,
      "change_24h": -5.184938832024832,
      "change_7d": 4.51178315130241,
      "market_cap": 1444477231,
      "id": "kaspa",
      "name": "Kaspa",
      "source": "coingecko"
    },
    "VET": {
      "usd": 0.01583584,
      "change_24h": -4.265479201634897,
      "change_7d": -8.552092322303638,
      "market_cap": 1361490407,
      "id": "vechain",
      "name": "VeChain",
      "source": "coingecko"
    },
    "PENGU": {
      "usd": 0.01877637,
      "change_24h": -8.350847392517299,
      "change_7d": -10.603232975123266,
      "market_cap": 1181637950,
      "id": "pudgy-penguins",
      "name": "Pudgy Penguins",
      "source": "coingecko"
    },
    "RENDER": {
      "usd": 2.25,
      "change_24h": -4.596678937434939,
      "change_7d": -9.808777991872649,
      "market_cap": 1166608967,
      "id": "render-token",
      "name": "Render",
      "source": "coingecko"
    },
    "SEI": {
      "usd": 0.185956,
      "change_24h": -4.763065703504237,
      "change_7d": -4.867943628350852,
      "market_cap": 1162247342,
      "id": "sei-network",
      "name": "Sei",
      "source": "coingecko"
    },
    "FIL": {
      "usd": 1.5,
      "change_24h": -3.3812372408954654,
      "change_7d": -4.884535746063669,
      "market_cap": 1053338677,
      "id": "filecoin",
      "name": "Filecoin",
      "source": "coingecko"
    },
    "BONK": {
      "usd": 0.00001355,
      "change_24h": -4.834211591179245,
      "change_7d": -8.057086327862663,
      "market_cap": 1048849025,
      "id": "bonk",
      "name": "Bonk",
      "source": "coingecko"
    },
    "IMX": {
      "usd": 0.494411,
      "change_24h": -3.629805155134812,
      "change_7d": -5.873267546074832,
      "market_cap": 971421154,
      "id": "immutable-x",
      "name": "Immutable",
      "source": "coingecko"
    },
    "OP": {
      "usd": 0.400258,
      "change_24h": -7.383904852727056,
      "change_7d": -9.569747806710028,
      "market_cap": 759342370,
      "id": "optimism",
      "name": "Optimism",
      "source": "coingecko"
    },
    "GRT": {
      "usd": 0.061313,
      "change_24h": -2.5849861661589077,
      "change_7d": -5.772491056338237,
      "market_cap": 647602794,
      "id": "the-graph",
      "name": "The Graph",
      "source": "coingecko"
    },
    "CFX": {
      "usd": 0.101989,
      "change_24h": -5.295136121275764,
      "change_7d": -8.565047261060034,
      "market_cap": 525452814,
      "id": "conflux-token",
      "name": "Conflux",
      "source": "coingecko"
    },
    "GALA": {
      "usd": 0.01007331,
      "change_24h": -4.9704845422273225,
      "change_7d": -8.775281806702145,
      "market_cap": 467958025,
      "id": "gala",
      "name": "GALA",
      "source": "coingecko"
    },
    "FLOW": {
      "usd": 0.262796,
      "change_24h": -1.4176571689890067,
      "change_7d": -5.209713564698271,
      "market_cap": 425478447,
      "id": "flow",
      "name": "Flow",
      "source": "coingecko"
    },
    "RUNE": {
      "usd": 0.842107,
      "change_24h": -3.1727173341782273,
      "change_7d": -2.160987896526859,
      "market_cap": 295845462,
      "id": "thorchain",
      "name": "THORChain",
      "source": "coingecko"
    },
    "FRAX": {
      "usd": 0.995651,
      "change_24h": -0.006609443251739169,
      "change_7d": -0.04603633582175356,
      "market_cap": 290846485,
      "id": "frax",
      "name": "Legacy Frax Dollar",
      "source": "coingecko"
    },
    "MINA": {
      "usd": 0.095042,
      "change_24h": -3.5889964720912,
      "change_7d": -10.268710308463687,
      "market_cap": 119690046,
      "id": "mina-protocol",
      "name": "Mina Protocol",
      "source": "coingecko"
    },
    "BOME": {
      "usd": 0.00096957,
      "change_24h": -5.224716618506034,
      "change_7d": -10.792006815254704,
      "market_cap": 66926829,
      "id": "book-of-meme",
      "name": "BOOK OF MEME",
      "source": "coingecko"
    },
    "GOAT": {
      "usd": 0.04908786,
      "change_24h": -6.118777815591278,
      "change_7d": -7.896428634038238,
      "market_cap": 49078557,
      "id": "goatseus-maximus",
      "name": "Goatseus Maximus",
      "source": "coingecko"
    },
    "STREAM": {
      "usd": 0.02906928,
      "change_24h": -10.643200332849121,
      "change_7d": -14.542448283058848,
      "market_cap": 3956226,
      "id": "streamflow",
      "name": "Streamflow",
      "source": "coingecko"
    },
    "CHILLGUY": {
      "usd": 0.0001793,
      "change_24h": -1.735431687260465,
      "change_7d": -2.890627527468154,
      "market_cap": 179547,
      "id": "just-a-chill-guy",
      "name": "Just a chill guy (ETH)",
      "source": "coingecko"
    },
    "FTM": {
      "usd": 0.180728,
      "change_24h": -10.630811873604763,
      "change_7d": 4.717198314867059,
      "market_cap": 0,
      "id": "fantom",
      "name": "Fantom",
      "source": "coingecko"
    },
    "MKR": {
      "usd": 1351.6,
      "change_24h": -5.006873294038989,
      "change_7d": -5.877865748125009,
      "market_cap": 0,
      "id": "maker",
      "name": "Maker",
      "source": "coingecko"
    }
  }
}