{
  "updated_at": "2025-10-31T06:46:56.542Z",
  "meta": {
    "included_ids": [
      "bitcoin",
      "ethereum",
      "tether",
      "binancecoin",
      "solana",
      "ripple",
      "usd-coin",
      "staked-ether",
      "cardano",
      "dogecoin",
      "avalanche-2",
      "tron",
      "shiba-inu",
      "wrapped-bitcoin",
      "polkadot",
      "chainlink",
      "bitcoin-cash",
      "uniswap",
      "litecoin",
      "internet-computer",
      "dai",
      "near",
      "ethereum-classic",
      "filecoin",
      "aptos",
      "leo-token",
      "stellar",
      "okb",
      "vechain",
      "render-token",
      "monero",
      "arbitrum",
      "fantom",
      "the-graph",
      "immutable-x",
      "maker",
      "kaspa",
      "gala",
      "optimism",
      "frax",
      "sei-network",
      "algorand",
      "flow",
      "thorchain",
      "conflux-token",
      "mina-protocol",
      "worldcoin-wld",
      "polygon-ecosystem-token",
      "bonk",
      "book-of-meme",
      "official-trump",
      "streamflow",
      "pudgy-penguins",
      "just-a-chill-guy",
      "goatseus-maximus"
    ],
    "wallet_resolved": [
      {
        "raw": "worldcoin",
        "resolved": "worldcoin-wld",
        "via": "override"
      },
      {
        "raw": "pol",
        "resolved": "polygon-ecosystem-token",
        "via": "override"
      },
      {
        "raw": "bonk",
        "resolved": "bonk",
        "via": "id"
      },
      {
        "raw": "bome",
        "resolved": "book-of-meme",
        "via": "override"
      },
      {
        "raw": "official-trump",
        "resolved": "official-trump",
        "via": "id"
      },
      {
        "raw": "streamflow",
        "resolved": "streamflow",
        "via": "id"
      },
      {
        "raw": "pengu",
        "resolved": "pudgy-penguins",
        "via": "override"
      },
      {
        "raw": "just-a-chill-guy",
        "resolved": "just-a-chill-guy",
        "via": "id"
      },
      {
        "raw": "goatseus-maximus",
        "resolved": "goatseus-maximus",
        "via": "id"
      },
      {
        "raw": "optimism",
        "resolved": "optimism",
        "via": "id"
      },
      {
        "raw": "solana",
        "resolved": "solana",
        "via": "id"
      },
      {
        "raw": "ripple",
        "resolved": "ripple",
        "via": "id"
      }
    ],
    "missing": [],
    "ambiguous": []
  },
  "assets": {
    "BTC": {
      "usd": 109550,
      "change_24h": -1.1904045531132383,
      "change_7d": -1.5678118999509276,
      "market_cap": 2184118110843,
      "id": "bitcoin",
      "name": "Bitcoin",
      "source": "coingecko"
    },
    "ETH": {
      "usd": 3825.35,
      "change_24h": -2.426732311289528,
      "change_7d": -3.802562655871337,
      "market_cap": 461647650786,
      "id": "ethereum",
      "name": "Ethereum",
      "source": "coingecko"
    },
    "USDT": {
      "usd": 0.999983,
      "change_24h": -0.024761553702943463,
      "change_7d": -0.04274884171187489,
      "market_cap": 183396396801,
      "id": "tether",
      "name": "Tether",
      "source": "coingecko"
    },
    "BNB": {
      "usd": 1093.08,
      "change_24h": -1.9750949395940454,
      "change_7d": -4.166801108723947,
      "market_cap": 150553496168,
      "id": "binancecoin",
      "name": "BNB",
      "source": "coingecko"
    },
    "XRP": {
      "usd": 2.48,
      "change_24h": -3.4414343172324826,
      "change_7d": 1.6350476587220324,
      "market_cap": 148964433520,
      "id": "ripple",
      "name": "XRP",
      "source": "coingecko"
    },
    "SOL": {
      "usd": 185.27,
      "change_24h": -4.819159471481671,
      "change_7d": -4.539943472107941,
      "market_cap": 101873805493,
      "id": "solana",
      "name": "Solana",
      "source": "coingecko"
    },
    "USDC": {
      "usd": 0.999799,
      "change_24h": -0.001095225762031783,
      "change_7d": -0.004324246105836752,
      "market_cap": 75842198047,
      "id": "usd-coin",
      "name": "USDC",
      "source": "coingecko"
    },
    "STETH": {
      "usd": 3825.99,
      "change_24h": -2.1024209890212546,
      "change_7d": -3.8613017624572343,
      "market_cap": 32890024880,
      "id": "staked-ether",
      "name": "Lido Staked Ether",
      "source": "coingecko"
    },
    "DOGE": {
      "usd": 0.184355,
      "change_24h": -3.6365755324533913,
      "change_7d": -6.92570433554663,
      "market_cap": 27945904115,
      "id": "dogecoin",
      "name": "Dogecoin",
      "source": "coingecko"
    },
    "TRX": {
      "usd": 0.294815,
      "change_24h": -0.5219098395353504,
      "change_7d": -6.077467724420881,
      "market_cap": 27907767597,
      "id": "tron",
      "name": "TRON",
      "source": "coingecko"
    },
    "ADA": {
      "usd": 0.610369,
      "change_24h": -5.06207628664296,
      "change_7d": -6.428842949005108,
      "market_cap": 22317453456,
      "id": "cardano",
      "name": "Cardano",
      "source": "coingecko"
    },
    "WBTC": {
      "usd": 109699,
      "change_24h": -0.7519790025166492,
      "change_7d": -1.3315646916864228,
      "market_cap": 13906576289,
      "id": "wrapped-bitcoin",
      "name": "Wrapped Bitcoin",
      "source": "coingecko"
    },
    "LINK": {
      "usd": 17.18,
      "change_24h": -5.555604795661939,
      "change_7d": -2.934412296643416,
      "market_cap": 11967381770,
      "id": "chainlink",
      "name": "Chainlink",
      "source": "coingecko"
    },
    "BCH": {
      "usd": 550.87,
      "change_24h": -3.2140115565587415,
      "change_7d": 12.975494007021455,
      "market_cap": 10981134360,
      "id": "bitcoin-cash",
      "name": "Bitcoin Cash",
      "source": "coingecko"
    },
    "XLM": {
      "usd": 0.301683,
      "change_24h": -4.660312505664601,
      "change_7d": -4.745562011138288,
      "market_cap": 9667189107,
      "id": "stellar",
      "name": "Stellar",
      "source": "coingecko"
    },
    "LEO": {
      "usd": 9.6,
      "change_24h": -0.1813566778507165,
      "change_7d": 6.986468959497991,
      "market_cap": 8851865068,
      "id": "leo-token",
      "name": "LEO Token",
      "source": "coingecko"
    },
    "AVAX": {
      "usd": 18.38,
      "change_24h": -6.803892980637845,
      "change_7d": -6.362361969775297,
      "market_cap": 7839926568,
      "id": "avalanche-2",
      "name": "Avalanche",
      "source": "coingecko"
    },
    "LTC": {
      "usd": 94.01,
      "change_24h": -4.58771341549581,
      "change_7d": -1.7763746163132896,
      "market_cap": 7189421841,
      "id": "litecoin",
      "name": "Litecoin",
      "source": "coingecko"
    },
    "XMR": {
      "usd": 321.21,
      "change_24h": -2.6855471323516773,
      "change_7d": -1.0938005498395877,
      "market_cap": 5922737849,
      "id": "monero",
      "name": "Monero",
      "source": "coingecko"
    },
    "SHIB": {
      "usd": 0.00000982,
      "change_24h": -2.8099736010979828,
      "change_7d": -3.700058105251368,
      "market_cap": 5787684861,
      "id": "shiba-inu",
      "name": "Shiba Inu",
      "source": "coingecko"
    },
    "DAI": {
      "usd": 0.999948,
      "change_24h": 0.016008453166647712,
      "change_7d": 0.18833754157880905,
      "market_cap": 4642034457,
      "id": "dai",
      "name": "Dai",
      "source": "coingecko"
    },
    "DOT": {
      "usd": 2.9,
      "change_24h": -5.5158898282190725,
      "change_7d": -5.25581897591657,
      "market_cap": 4411573249,
      "id": "polkadot",
      "name": "Polkadot",
      "source": "coingecko"
    },
    "UNI": {
      "usd": 5.93,
      "change_24h": -2.500254891021542,
      "change_7d": -7.435840761724452,
      "market_cap": 3559285009,
      "id": "uniswap",
      "name": "Uniswap",
      "source": "coingecko"
    },
    "OKB": {
      "usd": 148.41,
      "change_24h": -5.718117496762676,
      "change_7d": -10.069244738890507,
      "market_cap": 3116699087,
      "id": "okb",
      "name": "OKB",
      "source": "coingecko"
    },
    "NEAR": {
      "usd": 2.11,
      "change_24h": -6.216297682521661,
      "change_7d": -6.1571218934808964,
      "market_cap": 2698631369,
      "id": "near",
      "name": "NEAR Protocol",
      "source": "coingecko"
    },
    "ETC": {
      "usd": 15.59,
      "change_24h": -1.8531297850943171,
      "change_7d": -1.855236419383817,
      "market_cap": 2403043205,
      "id": "ethereum-classic",
      "name": "Ethereum Classic",
      "source": "coingecko"
    },
    "APT": {
      "usd": 3.25,
      "change_24h": -3.6987455529363973,
      "change_7d": -0.29003876745385415,
      "market_cap": 2335167752,
      "id": "aptos",
      "name": "Aptos",
      "source": "coingecko"
    },
    "POL": {
      "usd": 0.186429,
      "change_24h": -3.9286563710049323,
      "change_7d": -4.3272389816285415,
      "market_cap": 1963081120,
      "id": "polygon-ecosystem-token",
      "name": "POL (ex-MATIC)",
      "source": "coingecko"
    },
    "WLD": {
      "usd": 0.805553,
      "change_24h": -5.042179468334796,
      "change_7d": -8.11385097176329,
      "market_cap": 1828562422,
      "id": "worldcoin-wld",
      "name": "Worldcoin",
      "source": "coingecko"
    },
    "ARB": {
      "usd": 0.291924,
      "change_24h": -7.287960711129855,
      "change_7d": -8.319255270689728,
      "market_cap": 1608199376,
      "id": "arbitrum",
      "name": "Arbitrum",
      "source": "coingecko"
    },
    "TRUMP": {
      "usd": 8.05,
      "change_24h": -1.8990675389786271,
      "change_7d": 35.95401164121703,
      "market_cap": 1606264953,
      "id": "official-trump",
      "name": "Official Trump",
      "source": "coingecko"
    },
    "ICP": {
      "usd": 2.91,
      "change_24h": -3.729884304347881,
      "change_7d": -6.436811178943749,
      "market_cap": 1570174235,
      "id": "internet-computer",
      "name": "Internet Computer",
      "source": "coingecko"
    },
    "ALGO": {
      "usd": 0.175942,
      "change_24h": -5.260411916750428,
      "change_7d": -4.473164741524536,
      "market_cap": 1546660705,
      "id": "algorand",
      "name": "Algorand",
      "source": "coingecko"
    },
    "KAS": {
      "usd": 0.05387,
      "change_24h": -5.960067772394129,
      "change_7d": 4.433120175247794,
      "market_cap": 1442579019,
      "id": "kaspa",
      "name": "Kaspa",
      "source": "coingecko"
    },
    "VET": {
      "usd": 0.01581715,
      "change_24h": -4.97810891850089,
      "change_7d": -8.660066730471218,
      "market_cap": 1360175494,
      "id": "vechain",
      "name": "VeChain",
      "source": "coingecko"
    },
    "PENGU": {
      "usd": 0.01872674,
      "change_24h": -9.071994943768688,
      "change_7d": -10.8395162095595,
      "market_cap": 1177872429,
      "id": "pudgy-penguins",
      "name": "Pudgy Penguins",
      "source": "coingecko"
    },
    "RENDER": {
      "usd": 2.24,
      "change_24h": -5.607157924156421,
      "change_7d": -9.93124483648727,
      "market_cap": 1164315326,
      "id": "render-token",
      "name": "Render",
      "source": "coingecko"
    },
    "SEI": {
      "usd": 0.185766,
      "change_24h": -5.266139904833699,
      "change_7d": -4.965090258069537,
      "market_cap": 1160405038,
      "id": "sei-network",
      "name": "Sei",
      "source": "coingecko"
    },
    "FIL": {
      "usd": 1.5,
      "change_24h": -3.849088982490693,
      "change_7d": -4.7278131421909455,
      "market_cap": 1057232175,
      "id": "filecoin",
      "name": "Filecoin",
      "source": "coingecko"
    },
    "BONK": {
      "usd": 0.00001353,
      "change_24h": -5.4146480347661745,
      "change_7d": -8.190708326548666,
      "market_cap": 1047036904,
      "id": "bonk",
      "name": "Bonk",
      "source": "coingecko"
    },
    "IMX": {
      "usd": 0.493433,
      "change_24h": -4.321664662599635,
      "change_7d": -6.059380564402784,
      "market_cap": 969111784,
      "id": "immutable-x",
      "name": "Immutable",
      "source": "coingecko"
    },
    "OP": {
      "usd": 0.398973,
      "change_24h": -7.972636950258269,
      "change_7d": -9.860025854149589,
      "market_cap": 756318173,
      "id": "optimism",
      "name": "Optimism",
      "source": "coingecko"
    },
    "GRT": {
      "usd": 0.061245,
      "change_24h": -3.187396040752668,
      "change_7d": -5.876813010311509,
      "market_cap": 647006249,
      "id": "the-graph",
      "name": "The Graph",
      "source": "coingecko"
    },
    "CFX": {
      "usd": 0.101714,
      "change_24h": -6.242466993681423,
      "change_7d": -8.811236889006615,
      "market_cap": 524192887,
      "id": "conflux-token",
      "name": "Conflux",
      "source": "coingecko"
    },
    "GALA": {
      "usd": 0.01005911,
      "change_24h": -5.86473815538135,
      "change_7d": -8.903829128192152,
      "market_cap": 467269625,
      "id": "gala",
      "name": "GALA",
      "source": "coingecko"
    },
    "FLOW": {
      "usd": 0.26245,
      "change_24h": -2.148216824944015,
      "change_7d": -5.334459582279387,
      "market_cap": 425030556,
      "id": "flow",
      "name": "Flow",
      "source": "coingecko"
    },
    "RUNE": {
      "usd": 0.841312,
      "change_24h": -3.955814337208467,
      "change_7d": -2.2533903650268425,
      "market_cap": 295528838,
      "id": "thorchain",
      "name": "THORChain",
      "source": "coingecko"
    },
    "FRAX": {
      "usd": 0.995522,
      "change_24h": -0.11225387769532018,
      "change_7d": -0.05896907618284344,
      "market_cap": 290732165,
      "id": "frax",
      "name": "Legacy Frax Dollar",
      "source": "coingecko"
    },
    "MINA": {
      "usd": 0.094944,
      "change_24h": -3.716656222342649,
      "change_7d": -10.36123648013156,
      "market_cap": 119589551,
      "id": "mina-protocol",
      "name": "Mina Protocol",
      "source": "coingecko"
    },
    "BOME": {
      "usd": 0.00096902,
      "change_24h": -5.492578581668795,
      "change_7d": -10.842719636468212,
      "market_cap": 66888605,
      "id": "book-of-meme",
      "name": "BOOK OF MEME",
      "source": "coingecko"
    },
    "GOAT": {
      "usd": 0.04897055,
      "change_24h": -6.525700157288034,
      "change_7d": -8.116541141004252,
      "market_cap": 49052148,
      "id": "goatseus-maximus",
      "name": "Goatseus Maximus",
      "source": "coingecko"
    },
    "STREAM": {
      "usd": 0.02908635,
      "change_24h": -10.623152918349286,
      "change_7d": -14.492263926966647,
      "market_cap": 3960053,
      "id": "streamflow",
      "name": "Streamflow",
      "source": "coingecko"
    },
    "CHILLGUY": {
      "usd": 0.0001793,
      "change_24h": 1.0022204347397314,
      "change_7d": -2.890627527468154,
      "market_cap": 179299,
      "id": "just-a-chill-guy",
      "name": "Just a chill guy (ETH)",
      "source": "coingecko"
    },
    "FTM": {
      "usd": 0.173789,
      "change_24h": -15.795461612721487,
      "change_7d": 0.6965599385384145,
      "market_cap": 0,
      "id": "fantom",
      "name": "Fantom",
      "source": "coingecko"
    },
    "MKR": {
      "usd": 1350.74,
      "change_24h": -5.239359577035703,
      "change_7d": -5.938212317091631,
      "market_cap": 0,
      "id": "maker",
      "name": "Maker",
      "source": "coingecko"
    }
  }
}